Workbook

Sheet ALL
A1: ID | B1: MC | C1: Q1ab | D1: Q1ab(Notes) | E1: Q1c-e | F1: Q1c-e(Notes) | G1: Q2a-c | H1: Q2a-c(Notes) | I1: Q2-TM | J1: Q2-TM(Notes) | K1: Q2-box | L1: Q2-box(Notes) | M1: Short | N1: Short(Notes) | O1: Class
B2: 16 | C2: ='Q1a-b'!F2 -> 55 | D2: ='Q1a-b'!G2 -> 0 | E2: ='Q1c-e'!E2 -> 20 | G2: ='Q2a-(C)'!K2 -> 40 | I2: ='Q2-TM'!E2 -> 16 | J2: ='Q2-TM'!F2 -> 0 | K2: ='Q2-Box'!F2 -> 16 | L2: ='Q2-Box'!G2 -> 0 | M2: ='short answer'!L3 -> 22.5 | N2: ='short answer'!M3 -> 0
C3: ='Q1a-b'!F3 -> 0 | D3: ='Q1a-b'!G3 -> 0 | E3: ='Q1c-e'!E3 -> 0 | G3: ='Q2a-(C)'!K3 -> 0 | I3: ='Q2-TM'!E3 -> 0 | J3: ='Q2-TM'!F3 -> 0 | K3: ='Q2-Box'!F3 -> 0 | L3: ='Q2-Box'!G3 -> 0 | M3: ='short answer'!L4 -> 0 | N3: ='short answer'!M4 -> 0
A4: 1248 | B4: 10 | C4: ='Q1a-b'!F4 -> 40 | D4: ='Q1a-b'!G4 -> 0 | E4: ='Q1c-e'!E4 -> 6 | F4: ='Q1c-e'!F4 -> 0 9/3 R/A; assume TS misapp; 103 bc iceland holder | G4: ='Q2a-(C)'!K4 -> 18 | H4: ='Q2a-(C)'!L4 -> 0 | I4: ='Q2-TM'!E4 -> 4.5 | J4: ='Q2-TM'!F4 -> inf source? | K4: ='Q2-Box'!F4 -> 10 | L4: ='Q2-Box'!G4 -> 0 | M4: ='short answer'!L5 -> 16 | N4: ='short answer'!M5 -> Q3-no TS | O4: 110.5
A5: 1889 | B5: 6 | C5: ='Q1a-b'!F5 -> 37 | D5: ='Q1a-b'!G5 -> inv date = patent??; 102 conclu (dnt expln why not all elemnets); | E5: ='Q1c-e'!E5 -> 4.5 | F5: ='Q1c-e'!F5 -> think fails not easily ID w/o; no TS bc got patent?; 103 | G5: ='Q2a-(C)'!K5 -> 30 | H5: ='Q2a-(C)'!L5 -> EA gist, but 2 sent | I5: ='Q2-TM'!E5 -> 12.5 | J5: ='Q2-TM'!F5 -> 0 | K5: ='Q2-Box'!F5 -> 8 | L5: ='Q2-Box'!G5 -> not used on good/srvc bc not for sale | M5: ='short answer'!L6 -> 13.5 | N5: ='short answer'!M6 -> Q3-no TS; Q8-dgital | O5: 100.69
A6: 2099 | B6: 10 | C6: ='Q1a-b'!F6 -> 40.5 | D6: ='Q1a-b'!G6 -> 0 | E6: ='Q1c-e'!E6 -> 11.5 | F6: ='Q1c-e'!F6 -> think nom fair use fine; 0 on whether ec valu; | G6: ='Q2a-(C)'!K6 -> 34 | H6: ='Q2a-(C)'!L6 -> video thin bc factual? | I6: ='Q2-TM'!E6 -> 8 | J6: ='Q2-TM'!F6 -> 0 | K6: ='Q2-Box'!F6 -> 3 | L6: ='Q2-Box'!G6 -> 0 | M6: ='short answer'!L7 -> 7.5 | N6: ='short answer'!M7 -> Q6-diution!; | O6: 111.19
A7: 2410 | B7: 16 | C7: ='Q1a-b'!F7 -> 50 | D7: ='Q1a-b'!G7 -> great 2d - copying AFTER shark tank | E7: ='Q1c-e'!E7 -> 11.5 | F7: ='Q1c-e'!F7 -> 0 3rd cir A; think TS claim; 103 | G7: ='Q2a-(C)'!K7 -> 32.5 | H7: ='Q2a-(C)'!L7 -> 0 | I7: ='Q2-TM'!E7 -> 14.5 | J7: ='Q2-TM'!F7 -> 0 | K7: ='Q2-Box'!F7 -> 12 | L7: ='Q2-Box'!G7 -> box not sold in commerce | M7: ='short answer'!L8 -> 17 | N7: ='short answer'!M8 -> Q9-right side only | O7: 111.6
A8: 2809 | B8: 10 | C8: ='Q1a-b'!F8 -> 43 | D8: ='Q1a-b'!G8 -> 0 | E8: ='Q1c-e'!E8 -> 13 | F8: ='Q1c-e'!F8 -> nom test, but no A; not reas secret; not valu bc knockoffs | G8: ='Q2a-(C)'!K8 -> 13 | H8: ='Q2a-(C)'!L8 -> ER liable bc 0 transf for fair use | I8: ='Q2-TM'!E8 -> 1.5 | J8: ='Q2-TM'!F8 -> TM presumed valid | K8: ='Q2-Box'!F8 -> 7 | L8: ='Q2-Box'!G8 -> think req sale, but conclu say not fxn and need 2d meaning; © conclu | M8: ='short answer'!L9 -> 8.5 | N8: ='short answer'!M9 -> 0 | O8: 109.46
A9: 3071 | B9: 8 | C9: ='Q1a-b'!F9 -> 35 | D9: ='Q1a-b'!G9 -> jill exptl use 102?; 103 -obv bc iceland; got shark tank and copying not nec due to inv or shark | E9: ='Q1c-e'!E9 -> 3 | F9: ='Q1c-e'!F9 -> fails 9 bc assoc? (and 3d cir); no recc | G9: ='Q2a-(C)'!K9 -> 21 | H9: ='Q2a-(C)'!L9 -> 0 | I9: ='Q2-TM'!E9 -> 10.5 | J9: ='Q2-TM'!F9 -> lgo argu generic, and then descrip | K9: ='Q2-Box'!F9 -> 3.5 | L9: ='Q2-Box'!G9 -> 0 | M9: ='short answer'!L10 -> 8 | N9: ='short answer'!M10 -> Q8-no if pub comain | O9: 103.37
A10: 3470 | B10: 16 | C10: ='Q1a-b'!F10 -> 45.5 | D10: ='Q1a-b'!G10 -> 0 | E10: ='Q1c-e'!E10 -> 15.5 | F10: ='Q1c-e'!F10 -> could be ec valu; got 102(b) | G10: ='Q2a-(C)'!K10 -> 25 | H10: ='Q2a-(C)'!L10 -> 0 | I10: ='Q2-TM'!E10 -> 12 | J10: ='Q2-TM'!F10 -> 0 | K10: ='Q2-Box'!F10 -> 8.5 | L10: ='Q2-Box'!G10 -> 0 | M10: ='short answer'!L11 -> 13.5 | N10: ='short answer'!M11 -> 0 | O10: 111.38
A11: 3757 | B11: 10 | C11: ='Q1a-b'!F11 -> 22 | D11: ='Q1a-b'!G11 -> 0 construc besides "at least"; 102- no inv date; GR/pillow for 102(a)?; 102(b) bar iceland | E11: ='Q1c-e'!E11 -> 8.5 | F11: ='Q1c-e'!F11 -> "likely nom" w/o explnl; think TS misapp; noted unikely exptl use for 102 | G11: ='Q2a-(C)'!K11 -> 7.5 | H11: ='Q2a-(C)'!L11 -> think EA inf both, but no liability method only bc method not © | I11: ='Q2-TM'!E11 -> 1 | J11: ='Q2-TM'!F11 -> no good/servv with video? | K11: ='Q2-Box'!F11 -> 6 | L11: ='Q2-Box'!G11 -> TD defn; req use in commerce | M11: ='short answer'!L12 -> 5 | N11: ='short answer'!M12 -> Q9-only fail if simple shape/phrase | O11: 99.18
A12: 4037 | B12: 10 | C12: ='Q1a-b'!F12 -> 41 | D12: ='Q1a-b'!G12 -> 103 - "almost all elements" | E12: ='Q1c-e'!E12 -> 8.5 | F12: ='Q1c-e'!F12 -> 0 Rule/A nom; TS misapp IF TS; 102(b) overcome if files w/tihin 1 yr? | G12: ='Q2a-(C)'!K12 -> 22 | H12: ='Q2a-(C)'!L12 -> 0 | I12: ='Q2-TM'!E12 -> 8 | J12: ='Q2-TM'!F12 -> 0 | K12: ='Q2-Box'!F12 -> 3.5 | L12: ='Q2-Box'!G12 -> scope only for TD | M12: ='short answer'!L13 -> 15 | N12: ='short answer'!M13 -> Q8-"making new"; Q9-notes/phone not ©? | O12: 109.03
A13: 4234 | B13: 12 | C13: ='Q1a-b'!F13 -> 27 | D13: ='Q1a-b'!G13 -> 1 p all patent; 103-pillow field; prob display; GR "sim prob"; 0 diff/motiv/2d | E13: ='Q1c-e'!E13 -> 14 | F13: ='Q1c-e'!F13 -> 0A nom (got rules); TS misapp | G13: ='Q2a-(C)'!K13 -> 21 | H13: ='Q2a-(C)'!L13 -> EA- no hero | I13: ='Q2-TM'!E13 -> 7 | J13: ='Q2-TM'!F13 -> 0 | K13: ='Q2-Box'!F13 -> 9.5 | L13: ='Q2-Box'!G13 -> not used in commerce bc no sales | M13: ='short answer'!L14 -> 16 | N13: ='short answer'!M14 -> Q8-digital | O13: 101.95
A14: 4239 | B14: 10 | C14: ='Q1a-b'!F14 -> 35.5 | D14: ='Q1a-b'!G14 -> field = lap desk; 0 expln of JP etc for analog | E14: ='Q1c-e'!E14 -> 14.5 | F14: ='Q1c-e'!F14 -> skip 3d cir A; | G14: ='Q2a-(C)'!K14 -> 30 | H14: ='Q2a-(C)'!L14 -> EA no expln | I14: ='Q2-TM'!E14 -> 9 | J14: ='Q2-TM'!F14 -> 0 | K14: ='Q2-Box'!F14 -> 8 | L14: ='Q2-Box'!G14 -> bullets | M14: ='short answer'!L15 -> 13.5 | N14: ='short answer'!M15 -> 0 | O14: 108.13
A15: 4606 | B15: 4 | C15: ='Q1a-b'!F15 -> 8.5 | D15: ='Q1a-b'!G15 -> 0 claim construc; DOE; both inf; Iceland A; 0 comparison of art to inv or 2d | E15: ='Q1c-e'!E15 -> 5 | F15: ='Q1c-e'!F15 -> missing nom fair use facrtors; no TS misappro bc not reas secrecy; prod changed? | G15: ='Q2a-(C)'!K15 -> 0 | H15: ='Q2a-(C)'!L15 -> fair use weak, altho got unlikely fair (D use to create logo?) | I15: ='Q2-TM'!E15 -> 4.5 | J15: ='Q2-TM'!F15 -> 0 | K15: ='Q2-Box'!F15 -> 4.5 | L15: ='Q2-Box'!G15 -> "local" TD and not useful?; broad protection unfair | M15: ='short answer'!L16 -> 6.5 | N15: ='short answer'!M16 -> Q1-not to ID co;Q5-would be useful (unclear) | O15: 92.65
... A28: 9582 | B28: 12 | C28: ='Q1a-b'!F28 -> 41.5 | D28: ='Q1a-b'!G28 -> miss L not all edge; 102(a) > 1 yr?; confused field v. prob; but got 1 edge v. all | E28: ='Q1c-e'!E28 -> 10 | F28: ='Q1c-e'!F28 -> think 9cir prob; no 3d Cir A; not reas secret; prior art by prior patent | G28: ='Q2a-(C)'!K28 -> 30 | H28: ='Q2a-(C)'!L28 -> 0 single bound; cc, but owise ok inf; 107 - all but mention why min transf v. Dr. Sues & equiv mkt | I28: ='Q2-TM'!E28 -> 8 | J28: ='Q2-TM'!F28 -> 0 | K28: ='Q2-Box'!F28 -> 7.5 | L28: ='Q2-Box'!G28 -> 0 | M28: ='short answer'!L29 -> 13.5 | N28: ='short answer'!M29 -> Q1-not using Lyft | O28: 113.1

Sheet Q1a-b
A1: ID | C1: Infring | D1: 102 | E1: 103 | G1: Notes
A2: MAX | C2: 25 | D2: 12 | E2: 18 | F2: =SUM(C2:E2) -> 55
A4: 1248 | C4: 18.5 | D4: 9 | E4: 12.5 | F4: =SUM(C4:E4) -> 40
A5: 1889 | C5: 20 | D5: 5 | E5: 12 | F5: =SUM(C5:E5) -> 37 | G5: inv date = patent??; 102 conclu (dnt expln why not all elemnets);
A6: 2099 | C6: 14.5 | D6: 12 | E6: 14 | F6: =SUM(C6:E6) -> 40.5
A7: 2410 | C7: 23 | D7: 10 | E7: 17 | F7: =SUM(C7:E7) -> 50 | G7: great 2d - copying AFTER shark tank
A8: 2809 | C8: 21.5 | D8: 10.5 | E8: 11 | F8: =SUM(C8:E8) -> 43
A9: 3071 | C9: 23.5 | D9: 7 | E9: 4.5 | F9: =SUM(C9:E9) -> 35 | G9: jill exptl use 102?; 103 -obv bc iceland; got shark tank and copying not nec due to inv or shark
A10: 3470 | C10: 22 | D10: 11 | E10: 12.5 | F10: =SUM(C10:E10) -> 45.5
A11: 3757 | C11: 15 | D11: 2 | E11: 5 | F11: =SUM(C11:E11) -> 22 | G11: 0 construc besides "at least"; 102- no inv date; GR/pillow for 102(a)?; 102(b) bar iceland
A12: 4037 | C12: 20 | D12: 12 | E12: 9 | F12: =SUM(C12:E12) -> 41 | G12: 103 - "almost all elements"
A13: 4234 | C13: 15 | D13: 7.5 | E13: 4.5 | F13: =SUM(C13:E13) -> 27 | G13: 1 p all patent; 103-pillow field; prob display; GR "sim prob"; 0 diff/motiv/2d
A14: 4239 | C14: 18 | D14: 8 | E14: 9.5 | F14: =SUM(C14:E14) -> 35.5 | G14: field = lap desk; 0 expln of JP etc for analog
A15: 4606 | C15: 4.5 | D15: 3 | E15: 1 | F15: =SUM(C15:E15) -> 8.5 | G15: 0 claim construc; DOE; both inf; Iceland A; 0 comparison of art to inv or 2d
A16: 5010 | C16: 14.5 | D16: 10.5 | E16: 7.5 | F16: =SUM(C16:E16) -> 32.5 | G16: confu construc-think PH does NOT limit?; 103-no diff ID/A; no 2d consid
A17: 6519 | C17: 19.5 | D17: 8 | E17: 8 | F17: =SUM(C17:E17) -> 35.5 | G17: construc sorta unclear; but good A; 102(a)-tweet?; no inv expln; 103 bulleted
A18: 6571 | C18: 19 | D18: 11 | E18: 10 | F18: =SUM(C18:E18) -> 40 | G18: sortta cursory inf A;
A19: 6785 | C19: 11.5 | D19: 11 | E19: 15 | F19: =SUM(C19:E19) -> 37.5 | G19: sortta cursory inf A; good 2d consid
A20: 7395 | C20: 5 | D20: 0 | E20: 1 | F20: =SUM(C20:E20) -> 6 | G20: 0 construc; inf "A" is Y/N 103 almost 0 - lists art and says no motiv combine and likely pat
A21: 7416 | C21: 17.5 | D21: 12 | E21: 14 | F21: =SUM(C21:E21) -> 43.5 | G21: PP missing edge?; got shak Tank, but think copying rebuts 103
A22: 7531 | C22: 21.5 | D22: 11 | E22: 14 | F22: =SUM(C22:E22) -> 46.5 | G22: miss Lamical 2 sides;pillow NA?; diff = 3 edge and soft triangle
... A28: 9582 | C28: 19.5 | D28: 9 | E28: 13 | F28: =SUM(C28:E28) -> 41.5 | G28: miss L not all edge; 102(a) > 1 yr?; confused field v. prob; but got 1 edge v. all
A30: AVG | C30: =AVERAGE(C4:C28) -> 17.34 | D30: =AVERAGE(D4:D28) -> 8.76 | E30: =AVERAGE(E4:E28) -> 9.2
A31: STD | C31: =STDEV(C4:C28) -> 4.8856081 | D31: =STDEV(D4:D28) -> 3.2310989 | E31: =STDEV(E4:E28) -> 4.4628093
A33: minus 1 | C33: =C30-C31 -> 12.454392 | D33: =D30-D31 -> 5.5289011 | E33: =E30-E31 -> 4.7371907
A34: minus 2 | C34: =C33-C31 -> 7.5687838 | D34: =D33-D31 -> 2.2978022 | E34: =E33-E31 -> 0.27438144
A36: plus 1

Sheet Q1c-e
B1: 1c | C1: 1d | D1: 1e | F1: Notes
B2: 10 | C2: 5 | D2: 5 | E2: =SUM(B2:D2) -> 20
A4: 1248 | B4: 3.5 | C4: 1.5 | D4: 1 | E4: =SUM(B4:D4) -> 6 | F4: 0 9/3 R/A; assume TS misapp; 103 bc iceland holder
A5: 1889 | B5: 3 | C5: 0.5 | D5: 1 | E5: =SUM(B5:D5) -> 4.5 | F5: think fails not easily ID w/o; no TS bc got patent?; 103
A6: 2099 | B6: 6.5 | C6: 1 | D6: 4 | E6: =SUM(B6:D6) -> 11.5 | F6: think nom fair use fine; 0 on whether ec valu;
A7: 2410 | B7: 8 | C7: 2.5 | D7: 1 | E7: =SUM(B7:D7) -> 11.5 | F7: 0 3rd cir A; think TS claim; 103
A8: 2809 | B8: 5 | C8: 3 | D8: 5 | E8: =SUM(B8:D8) -> 13 | F8: nom test, but no A; not reas secret; not valu bc knockoffs
A9: 3071 | B9: 3 | C9: 0 | D9: 0 | E9: =SUM(B9:D9) -> 3 | F9: fails 9 bc assoc? (and 3d cir); no recc
A10: 3470 | B10: 8.5 | C10: 2 | D10: 5 | E10: =SUM(B10:D10) -> 15.5 | F10: could be ec valu; got 102(b)
A11: 3757 | B11: 2 | C11: 1.5 | D11: 5 | E11: =SUM(B11:D11) -> 8.5 | F11: "likely nom" w/o explnl; think TS misapp; noted unikely exptl use for 102
A12: 4037 | B12: 3.5 | C12: 2 | D12: 3 | E12: =SUM(B12:D12) -> 8.5 | F12: 0 Rule/A nom; TS misapp IF TS; 102(b) overcome if files w/tihin 1 yr?
A13: 4234 | B13: 7 | C13: 2 | D13: 5 | E13: =SUM(B13:D13) -> 14 | F13: 0A nom (got rules); TS misapp
A14: 4239 | B14: 8.5 | C14: 1 | D14: 5 | E14: =SUM(B14:D14) -> 14.5 | F14: skip 3d cir A;
A15: 4606 | B15: 2.5 | C15: 2.5 | D15: 0 | E15: =SUM(B15:D15) -> 5 | F15: missing nom fair use facrtors; no TS misappro bc not reas secrecy; prod changed?
... A28: 9582 | B28: 6.5 | C28: 2.5 | D28: 1 | E28: =SUM(B28:D28) -> 10 | F28: think 9cir prob; no 3d Cir A; not reas secret; prior art by prior patent
A30: AVG | B30: =AVERAGE(B4:B28) -> 4.72 | C30: =AVERAGE(C4:C28) -> 2.12 | D30: =AVERAGE(D4:D28) -> 2.96 | E30: =AVERAGE(E4:E28) -> 9.8
A31: STD | B31: =STDEV(B4:B28) -> 2.3142673 | C31: =STDEV(C4:C28) -> 1.2932517 | D31: =STDEV(D4:D28) -> 2.0305993 | E31: =STDEV(E4:E28) -> 4.1758233
A33: minus 1 | B33: =B30-B31 -> 2.4057327 | C33: =C30-C31 -> 0.82674828 | D33: =D30-D31 -> 0.92940075 | E33: =E30-E31 -> 5.6241767
A35: plus 1 | B35: =B30+B31 -> 7.0342673 | C35: =C30+C31 -> 3.4132517 | D35: =D30+D31 -> 4.9905993 | E35: =E30+E31 -> 13.975823

Sheet Q2a-(C)
A1: ID | C1: Inf | D1: 107 | F1: © basic | G1: method | H1: video | J1: EA | L1: Notes
A2: MAX | C2: 5 | D2: 12 | F2: 2 | G2: 5 | H2: 8 | J2: 8 | K2: =SUM(C2:J2) -> 40
A4: 1248 | C4: 5 | D4: 7.5 | F4: 0 | G4: 0 | H4: 0 | J4: 5.5 | K4: =SUM(C4:J4) -> 18
A5: 1889 | C5: 4.5 | D5: 6.5 | F5: 2 | G5: 4 | H5: 8 | J5: 5 | K5: =SUM(C5:J5) -> 30 | L5: EA gist, but 2 sent
A6: 2099 | C6: 4 | D6: 9.5 | F6: 2 | G6: 4.5 | H6: 6 | J6: 8 | K6: =SUM(C6:J6) -> 34 | L6: video thin bc factual?
A7: 2410 | C7: 4 | D7: 10 | F7: 2 | G7: 4.5 | H7: 6 | J7: 6 | K7: =SUM(C7:J7) -> 32.5
A8: 2809 | C8: 2 | D8: 10 | F8: 0 | G8: 0 | H8: 0 | J8: 1 | K8: =SUM(C8:J8) -> 13 | L8: ER liable bc 0 transf for fair use
A9: 3071 | C9: 3 | D9: 5 | F9: 1 | G9: 4 | H9: 3.5 | J9: 4.5 | K9: =SUM(C9:J9) -> 21
A10: 3470 | C10: 3.5 | D10: 9.5 | F10: 2 | G10: 5 | H10: 0 | J10: 5 | K10: =SUM(C10:J10) -> 25
A11: 3757 | C11: 2 | D11: 2 | F11: 1 | G11: 1 | H11: 0 | J11: 1.5 | K11: =SUM(C11:J11) -> 7.5 | L11: think EA inf both, but no liability method only bc method not ©
A12: 4037 | C12: 2 | D12: 7 | F12: 2 | G12: 4 | H12: 7 | J12: 0 | K12: =SUM(C12:J12) -> 22
A13: 4234 | C13: 3 | D13: 5 | F13: 2 | G13: 4 | H13: 2 | J13: 5 | K13: =SUM(C13:J13) -> 21 | L13: EA- no hero
A14: 4239 | C14: 4 | D14: 8 | F14: 2 | G14: 4 | H14: 8 | J14: 4 | K14: =SUM(C14:J14) -> 30 | L14: EA no expln
A15: 4606 | D15: 4 | F15: 1.5 | G15: 0.5 | H15: 0 | J15: 4 | L15: fair use weak, altho got unlikely fair (D use to create logo?)
A16: 5010 | C16: 3 | D16: 7 | F16: 2 | G16: 5 | H16: 2 | J16: 2.5 | K16: =SUM(C16:H16) -> 19 | L16: got phrase NA;
A17: 6519 | C17: 1 | D17: 3.5 | F17: 0 | G17: 1.5 | H17: 1.5 | J17: 5.5 | K17: =SUM(C17:H17) -> 7.5 | L17: noncomm; transf use
A18: 6571 | C18: 3.5 | D18: 9 | F18: 1 | G18: 2.5 | H18: 2 | J18: 5.5 | K18: =SUM(C18:H18) -> 18
A19: 6785 | C19: 3.5 | D19: 8 | F19: 0 | G19: 0 | H19: 0 | J19: 0.5 | K19: =SUM(C19:H19) -> 11.5 | L19: EA-0 hero; for method said expression might be ©, but 0 on inf
A20: 7395 | C20: 0.5 | D20: 1 | F20: 0 | G20: 0.25 | H20: 0.25 | J20: 2.5 | K20: =SUM(C20:H20) -> 2 | L20: 1 sent 107; lists copyrightable things?
A21: 7416 | C21: 2.5 | D21: 6.5 | F21: 0 | G21: 0 | H21: 0 | J21: 6.5 | K21: =SUM(C21:H21) -> 9 | L21: 107 ubcky single boud
A22: 7531 | C22: 3.5 | D22: 11 | F22: 0 | G22: 0 | H22: 0 | J22: 4.5 | K22: =SUM(C22:H22) -> 14.5
A23: 8236 | C23: 1.5 | D23: 0 | G23: 0.5 | H23: 0.5 | J23: 1 | K23: =SUM(C23:H23) -> 2.5 | L23: "weak © for asset
A24: 8868 | C24: 4 | D24: 7.5 | F24: 1 | G24: 5 | H24: 8 | J24: 2 | K24: =SUM(C24:H24) -> 25.5
A25: 9113 | C25: 2.5 | D25: 5.5 | F25: 0 | G25: 2.5 | H25: 4 | J25: 5.5 | K25: =SUM(C25:H25) -> 14.5
A26: 9194 | C26: 2 | D26: 2.5 | F26: 2 | G26: 1 | H26: 0 | J26: 2 | K26: =SUM(C26:H26) -> 7.5 | L26: no inf?; noncomm; transf work bc diff use?; took heart; not likely effect; method likely barred
A27: 9561 | C27: 3 | D27: 4.5 | F27: 0 | G27: 0 | H27: 0 | J27: 0 | K27: =SUM(C27:H27) -> 7.5 | L27: miss single bound un©; think noncomm; sim 2 live crew;
A28: 9582 | C28: 4 | D28: 11 | F28: 2 | G28: 5 | H28: 8 | J28: 3.5 | K28: =SUM(C28:H28) -> 30 | L28: 0 single bound; cc, but owise ok inf; 107 - all but mention why min transf v. Dr. Sues & equiv mkt

Sheet Q2-TM
C1: inf | D1: diu
A2: MAX | C2: 9 | D2: 7 | E2: =SUM(C2:D2) -> 16
A4: 1248 | C4: 4.5 | D4: 0 | E4: =SUM(C4:D4) -> 4.5 | F4: inf source?
A5: 1889 | C5: 8.5 | D5: 4 | E5: =SUM(C5:D5) -> 12.5
A6: 2099 | C6: 5 | D6: 3 | E6: =SUM(C6:D6) -> 8
A7: 2410 | C7: 9 | D7: 5.5 | E7: =SUM(C7:D7) -> 14.5
A8: 2809 | C8: 1.5 | D8: 0 | E8: =SUM(C8:D8) -> 1.5 | F8: TM presumed valid
A9: 3071 | C9: 6 | D9: 4.5 | E9: =SUM(C9:D9) -> 10.5 | F9: lgo argu generic, and then descrip
A10: 3470 | C10: 5 | D10: 7 | E10: =SUM(C10:D10) -> 12
A11: 3757 | C11: 1 | E11: =SUM(C11:D11) -> 1 | F11: no good/servv with video?
A12: 4037 | C12: 5 | D12: 3 | E12: =SUM(C12:D12) -> 8
A13: 4234 | C13: 5.5 | D13: 1.5 | E13: =SUM(C13:D13) -> 7
A14: 4239 | C14: 3 | D14: 6 | E14: =SUM(C14:D14) -> 9
A15: 4606 | C15: 3 | D15: 1.5 | E15: =SUM(C15:D15) -> 4.5
A16: 5010 | C16: 4.5 | D16: 5.5 | E16: =SUM(C16:D16) -> 10
A17: 6519 | C17: 5 | D17: 0 | E17: =SUM(C17:D17) -> 5
A18: 6571 | C18: 7.5 | D18: 0 | E18: =SUM(C18:D18) -> 7.5
A19: 6785 | C19: 3 | D19: 0 | E19: =SUM(C19:D19) -> 3
A20: 7395 | C20: 3 | D20: 0 | E20: =SUM(C20:D20) -> 3
A21: 7416 | C21: 4 | D21: 0 | E21: =SUM(C21:D21) -> 4
A22: 7531 | C22: 10 | D22: 5 | E22: =SUM(C22:D22) -> 15
A23: 8236 | C23: 0.5 | D23: 1 | E23: =SUM(C23:D23) -> 1.5 | F23: most important - not related, so know not sponsored?; not tarnish bc positive
A24: 8868 | C24: 2 | D24: 1.5 | E24: =SUM(C24:D24) -> 3.5
A25: 9113 | C25: 3 | D25: 4.5 | E25: =SUM(C25:D25) -> 7.5
A26: 9194 | C26: 3 | D26: 0 | E26: =SUM(C26:D26) -> 3
A27: 9561 | C27: 0.5 | D27: 0 | E27: =SUM(C27:D27) -> 0.5
A28: 9582 | C28: 2.5 | D28: 5.5 | E28: =SUM(C28:D28) -> 8
A30: AVG
A31: STD
A33: minus 1
A35: plus 1

Sheet Q2-Box
A1: ID | C1: Q2c-TD | D1: Q2c-© | E1: Q2c-scope | F1: Q2c | G1: Notes
A2: MAX | C2: 6 | D2: 7 | E2: 3 | F2: =SUM(C2:E2) -> 16
A4: 1248 | C4: 3.5 | D4: 3.5 | E4: 3 | F4: =SUM(C4:E4) -> 10
A5: 1889 | C5: 3 | D5: 5 | E5: 0 | F5: =SUM(C5:E5) -> 8 | G5: not used on good/srvc bc not for sale
A6: 2099 | C6: 0.5 | D6: 2.5 | E6: 0 | F6: =SUM(C6:E6) -> 3
A7: 2410 | C7: 3 | D7: 6 | E7: 3 | F7: =SUM(C7:E7) -> 12 | G7: box not sold in commerce
A8: 2809 | C8: 4.5 | D8: 2.5 | E8: 0 | F8: =SUM(C8:E8) -> 7 | G8: think req sale, but conclu say not fxn and need 2d meaning; © conclu
A9: 3071 | C9: 0 | D9: 3.5 | E9: 0 | F9: =SUM(C9:E9) -> 3.5
A10: 3470 | C10: 0.5 | D10: 5 | E10: 3 | F10: =SUM(C10:E10) -> 8.5
A11: 3757 | C11: 4 | D11: 2 | E11: 0 | F11: =SUM(C11:E11) -> 6 | G11: TD defn; req use in commerce
A12: 4037 | C12: 1 | D12: 0.5 | E12: 2 | F12: =SUM(C12:E12) -> 3.5 | G12: scope only for TD
A13: 4234 | C13: 3 | D13: 3.5 | E13: 3 | F13: =SUM(C13:E13) -> 9.5 | G13: not used in commerce bc no sales
A14: 4239 | C14: 3.5 | D14: 4.5 | E14: 0 | F14: =SUM(C14:E14) -> 8 | G14: bullets
A15: 4606 | C15: 1 | D15: 2.5 | E15: 1 | F15: =SUM(C15:E15) -> 4.5 | G15: "local" TD and not useful?; broad protection unfair
A16: 5010 | C16: 0.25 | D16: 0.25 | E16: 0 | F16: =SUM(C16:E16) -> 0.5 | G16: lists things s.a. tree image, instruc, etc
A17: 6519 | C17: 1.5 | D17: 0.5 | E17: 3 | F17: =SUM(C17:E17) -> 5 | G17: side branches aesthetic; need 2d meaning
A18: 6571 | C18: 3.5 | D18: 4 | E18: 0 | F18: =SUM(C18:E18) -> 7.5
A19: 6785 | C19: 5 | D19: 0 | E19: 0 | F19: =SUM(C19:E19) -> 5 | G19: box not useful art bc no util function
A20: 7395 | C20: 0.5 | D20: 0.5 | E20: 0 | F20: =SUM(C20:E20) -> 1 | G20: TD and copyright
A21: 7416 | C21: 6 | D21: 0 | E21: 2 | F21: =SUM(C21:E21) -> 8
A22: 7531 | C22: 5.5 | D22: 6.5 | E22: 2 | F22: =SUM(C22:E22) -> 14 | G22: TD if start selling; 0 A scope for copyright
A23: 8236 | C23: 2 | D23: 2 | E23: 0 | F23: =SUM(C23:E23) -> 4
A24: 8868 | C24: 3 | D24: 3.5 | E24: 3 | F24: =SUM(C24:E24) -> 9.5 | G24: not used on good/services for SALE in commerce if given to volunteers
A25: 9113 | C25: 5 | D25: 4 | E25: 0 | F25: =SUM(C25:E25) -> 9 | G25: provided volunteers = not in commerce
A26: 9194 | C26: 4 | D26: 3.5 | E26: 0 | F26: =SUM(C26:E26) -> 7.5 | G26: commerce likely bc ship; TD mostly rules
A27: 9561 | C27: 3 | D27: 0 | E27: 0 | F27: =SUM(C27:E27) -> 3 | G27: comm use is solicit funds
A28: 9582 | C28: 3.5 | D28: 4 | E28: 0 | F28: =SUM(C28:E28) -> 7.5

Sheet short answer
A1: ID | B1: Q1 | C1: Q2 | D1: Q3 | E1: Q4 | F1: Q5 | G1: Q6 | H1: Q7a | I1: Q7b | J1: Q8 | K1: Q9
B2: Lift | C2: straw | D2: PF | E2: artist | F2: rest | G2: (R) | H2: pub | I2: 106A | J2: sound | K2: calendar
A3: MAX | B3: 2 | C3: 2 | D3: 2.5 | E3: 3 | F3: 3 | G3: 2 | H3: 2 | I3: 1 | J3: 3 | K3: 2 | L3: =SUM(B3:K3) -> 22.5
A5: 1248 | B5: 1 | C5: 2 | D5: 1 | E5: 3 | F5: 1 | G5: 1 | H5: 2 | I5: 1 | J5: 2 | K5: 2 | L5: =SUM(B5:K5) -> 16 | M5: Q3-no TS
A6: 1889 | B6: 2 | C6: 2 | D6: 1 | E6: 0.5 | F6: 1 | G6: 2 | H6: 2 | I6: 1 | J6: 1 | K6: 1 | L6: =SUM(B6:K6) -> 13.5 | M6: Q3-no TS; Q8-dgital
A7: 2099 | B7: 2 | D7: 2 | F7: 0.5 | G7: -1 | I7: 1 | J7: 1 | K7: 2 | L7: =SUM(B7:K7) -> 7.5 | M7: Q6-diution!;
A8: 2410 | B8: 2 | C8: 2 | D8: 2 | E8: 3 | F8: 1 | G8: 2 | H8: 2 | I8: 1 | J8: 1 | K8: 1 | L8: =SUM(B8:K8) -> 17 | M8: Q9-right side only
A9: 2809 | B9: 2 | C9: 2 | D9: 2.5 | F9: 1 | G9: 1 | H9: 0 | I9: 0 | J9: 0 | K9: 0 | L9: =SUM(B9:K9) -> 8.5
A10: 3071 | B10: 0.5 | C10: 2 | D10: 2.5 | E10: 0 | F10: 0.5 | G10: 0.5 | H10: 0 | I10: 0.5 | J10: 0.5 | K10: 1 | L10: =SUM(B10:K10) -> 8 | M10: Q8-no if pub comain
A11: 3470 | B11: 2 | C11: 2 | D11: 2 | E11: 0.5 | F11: 2 | G11: 2 | I11: 1 | J11: 1 | K11: 1 | L11: =SUM(B11:K11) -> 13.5
A12: 3757 | B12: 0.5 | C12: 2 | D12: 1 | G12: 0.5 | K12: 1 | L12: =SUM(B12:K12) -> 5 | M12: Q9-only fail if simple shape/phrase
A13: 4037 | B13: 2 | C13: 2 | D13: 2.5 | F13: 1 | G13: 2 | H13: 2 | I13: 1 | J13: 2 | K13: 0.5 | L13: =SUM(B13:K13) -> 15 | M13: Q8-"making new"; Q9-notes/phone not ©?
A14: 4234 | B14: 2 | C14: 2 | D14: 2 | E14: 3 | F14: 3 | I14: 1 | J14: 1 | K14: 2 | L14: =SUM(B14:K14) -> 16 | M14: Q8-digital
A15: 4239 | B15: 2 | C15: 2 | D15: 2 | E15: 0.5 | F15: 1 | G15: 2 | H15: 2 | I15: 1 | K15: 1 | L15: =SUM(B15:K15) -> 13.5
A16: 4606 | B16: 1 | D16: 2 | E16: 1 | F16: 1.5 | G16: 0.5 | I16: 0.5 | L16: =SUM(B16:K16) -> 6.5 | M16: Q1-not to ID co;Q5-would be useful (unclear)
A17: 5010 | B17: 0 | C17: 1 | D17: 1.5 | H17: 2 | I17: 0.5 | J17: 0 | K17: 0 | L17: =SUM(B17:K17) -> 5 | M17: Q1-ord lang w/I mark;bar w/I country apply
A18: 6519 | B18: 1 | C18: 2 | D18: 1 | F18: 0 | G18: 0 | H18: 0 | I18: 0 | J18: 0 | K18: 0 | L18: =SUM(B18:K18) -> 4 | M18: Q1-not as a mark, but own goods/serv
A19: 6571 | B19: 1 | C19: 2 | D19: 2 | F19: 0.5 | G19: 0.5 | I19: 1 | J19: 3 | K19: 2 | L19: =SUM(B19:K19) -> 12 | M19: Q1-ord lang; 2 | Q19: .
A20: 6785 | B20: 0 | D20: 1 | F20: 0.5 | G20: 0 | J20: 1 | L20: =SUM(B20:K20) -> 2.5 | M20: Q1- "yes"; Q2 bkwards;Q8 "no liab"
A21: 7395 | B21: 0 | C21: 2 | D21: 2 | E21: 1 | F21: 1 | G21: 2 | H21: 1 | I21: 1 | J21: 2 | K21: 2 | L21: =SUM(B21:K21) -> 14 | M21: Q1 -ord lang to ID service; Q7-pub NA news
A22: 7416 | B22: 2 | C22: 2 | D22: 2.5 | E22: 3 | F22: 1 | G22: 2 | H22: 2 | I22: 1 | J22: 3 | K22: 1 | L22: =SUM(B22:K22) -> 19.5
A23: 7531 | B23: 1 | C23: 2 | D23: 2.5 | E23: 1 | F23: 0.5 | G23: 2 | H23: 2 | I23: 1 | J23: 1 | L23: =SUM(B23:K23) -> 13
A24: 8236 | B24: 2 | C24: 2 | D24: 1.5 | E24: 0.5 | F24: 0.5 | G24: 0.5 | H24: 1 | I24: 1 | J24: 0.5 | K24: 1 | L24: =SUM(B24:K24) -> 10.5 | M24: Q7-pub NA news; claim didn't have a lot of time to finish
A25: 8868 | B25: 2 | C25: 2 | D25: 2 | E25: 3 | F25: 1 | G25: 2 | H25: 2 | I25: 1 | J25: 0.5 | K25: 2 | L25: =SUM(B25:K25) -> 17.5
A26: 9113 | B26: 1 | C26: 2 | D26: 2 | F26: 0.5 | G26: 1 | I26: 1 | J26: 3 | K26: 2 | L26: =SUM(B26:K26) -> 12.5
A27: 9194 | B27: 1 | C27: 2 | D27: 2 | F27: 0.5 | G27: 0.5 | I27: 1 | L27: =SUM(B27:K27) -> 7 | M27: Q1-ord lang;
A28: 9561 | B28: 2 | C28: 2 | D28: 2.5 | E28: 0.5 | F28: 0.5 | G28: 1 | I28: -1 | J28: 1 | K28: 2 | L28: =SUM(B28:K28) -> 10.5
A29: 9582 | B29: 1.5 | C29: 2 | D29: 2.5 | F29: 0.5 | G29: 2 | I29: 1 | J29: 3 | K29: 1 | L29: =SUM(B29:K29) -> 13.5 | M29: Q1-not using Lyft
A31: average | B31: =AVERAGE(B5:B29) -> 1.34 | C31: =AVERAGE(C5:C29) -> 1.9545455 | D31: =AVERAGE(D5:D29) -> 1.9 | E31: =AVERAGE(E5:E29) -> 1.4642857 | F31: =AVERAGE(F5:F29) -> 0.89130435 | G31: =AVERAGE(G5:G29) -> 1.1304348 | H31: =AVERAGE(H5:H29) -> 1.4285714 | I31: =AVERAGE(I5:I29) -> 0.76086957 | ... L31: =AVERAGE(L5:L29) -> 11.26
A32: std | L32: =STDEV(L5:L29) -> 4.6258333
A34: plus 1 | L34: =L31+L32 -> 15.885833
A35: minus 1 | L35: =L31-L32 -> 6.6341667
A36: minus 2 | L36: =L35-L32 -> 2.0083335
